cookieconsent/__init__.py
cookieconsent/context.py
django_cookie_consent_compliance-0.0.6.dist-info/LICENSE
django_cookie_consent_compliance-0.0.6.dist-info/METADATA
django_cookie_consent_compliance-0.0.6.dist-info/WHEEL
django_cookie_consent_compliance-0.0.6.dist-info/top_level.txt
django_cookie_consent_compliance-0.0.6.dist-info/RECORD
