Metadata-Version: 2.2
Name: django-cookie-consent-compliance
Version: 0.0.6
Summary: A deterministic package allowing user consent implication for setting cookie on django projects
Author-email: pydevmans <mananbh9@live.com>
Project-URL: Homepage, https://github.com/pydevmans/cookieconsent
Project-URL: Issues, https://github.com/pydevmans/cookieconsent/issues
Classifier: Programming Language :: Python :: 3
Classifier: License :: OSI Approved :: MIT License
Classifier: Operating System :: OS Independent
Requires-Python: >=3.8
License-File: LICENSE
Requires-Dist: build>=1.2.2.post1
